README.md
setup.py
corvair/__init__.py
corvair.egg-info/PKG-INFO
corvair.egg-info/SOURCES.txt
corvair.egg-info/dependency_links.txt
corvair.egg-info/top_level.txt