Metadata-Version: 2.1
Name: corvair
Version: 0.0.1
Summary: A sitemap generator (both human-readible and indexable) for static sites.
Home-page: https://github.com/philipkiely/corvair
Author: Philip Kiely
Author-email: philip@kiely.xyz
License: UNKNOWN
Platform: UNKNOWN
Classifier: Programming Language :: Python :: 3
Classifier: License :: OSI Approved :: MIT License
Classifier: Operating System :: OS Independent
Requires-Python: >=3.6
